{
  "1327": {
    "name": "Kuroshio Kai",
    "dialogue": {
      "introduction": "I'm Kuroshio, nice to meet 'cha!",
      "library_intro": "Built in the Osaka Civilian Naval Yards, 3rd of the Kagerou-class Destroyers, Kuroshio. Even though I look like this, I participated in such hard-fought battles as Surabaya, the South Pacific and the third Battle of Solomon, ya' know.",
      "secretary1": "Chief, did'cha call me?",
      "secretary2": "Chief, what's up?",
      "secretary3": "Hey, there's nothing wrong with my body, y'know?",
      "secretaryidle": "Chief? Chieeef? Can yoouu heeeear me? ...Oh well. Guess I'll just take it easy then.",
      "secretarymarried": "It's no good to overwork yourself, chief. It worries us when we see it.",
      "wedding": "I... I'm... always lookin' at the chief, y'know? Really! C'mon, believe me...",
      "show_players_score": "Letter for the Chief!",
      "joining_a_fleet": "Well then, Kuroshio, off I go!",
      "equipment1": "Hawa~ This is good stuff!",
      "equipment2": "Whoa, somehow I'm gettin' stronger!",
      "equipment3": "Bit-by-bit~",
      "expedition_selection": "Bit-by-bit~",
      "resource_collection": "Bit-by-bit~",
      "instant_repair": "Bit-by-bit~",
      "development": "Bit-by-bit~",
      "supply": "Awesome, this will help~",
      "docking_minor_damage": "I'm just gonna rest for a bit~",
      "docking_moderate_damage": "Oww... I can't really bear this level of pain...",
      "docking_complete": "The ship repair has been finished?",
      "ship_construction": "A ship's construction is concluded",
      "return_from_sortie": "The fleet has returned~",
      "start_a_sortie": "Ooh~ sortieing! I can't wait!",
      "battle_start": "Enemy fleet spotted! C'mon, follow Kuroshio~!",
      "attack": "Hit 'em!",
      "night_battle": "Heheh, you ain't gettin' away!",
      "night_attack": "Direct hit!",
      "artillery_spotting": "Direct hit!",
      "night_special_attack_modifier_cutin_at_night_combat": "Direct hit!",
      "support_expedition_team_arrival": "Direct hit!",
      "mvp": "It just kind of happened that way, don't worry about me.",
      "minor_damaged1": "Woah!",
      "minor_damaged2": "Argh!",
      "moderately_damaged": "Man... this is bad...",
      "sunk": "I… I can't live any longer… Goodbye…",
      "second_anniversary_2015": "Commander, today is an anniversary right? Kuroshio is happy too!",
      "rainy_season_2015": "The rain huh. The season of rain, it is good in it's own way.",
      "midsummer_2015": "Chief? Why don't we go together to the sea? Nah, not to an expedition; to the sandy beach!",
      "christmas_2015": "Mmm! Christmas cake is delicous! Chief, say aaanh~",
      "end_of_year_2015": "This year is also about to end. Time to do cleaning.",
      "new_year_2016": "Admiral, it's new yea'. I'm countin' on you this year too.",
      "setsubun_2016": "Ehōmaki, huh~ Um, which direction it is this year? This way, is it? *nom*"
    },
    "hourly": {
    }
  }
}